setup.py
bin/nexg
nexg/__init__.py
nexg.egg-info/PKG-INFO
nexg.egg-info/SOURCES.txt
nexg.egg-info/dependency_links.txt
nexg.egg-info/not-zip-safe
nexg.egg-info/top_level.txt