Metadata-Version: 1.0
Name: nexg
Version: 0.0.1
Summary: Next Generation Sequencing Analysis Suite
Home-page: UNKNOWN
Author: nickytong
Author-email: ptong1@mdanderson.org
License: MIT
Platform: UNKNOWN
